LICENSE
freshdesk_sso/__init__.py
freshdesk_sso/apps.py
freshdesk_sso/urls.py
freshdesk_sso/views.py
django_freshdesk_sso-0.2.2.dist-info/LICENSE
django_freshdesk_sso-0.2.2.dist-info/WHEEL
django_freshdesk_sso-0.2.2.dist-info/METADATA
django_freshdesk_sso-0.2.2.dist-info/RECORD
