Metadata-Version: 2.1
Name: django-freshdesk-sso
Version: 0.2.2
Summary: Django Freshdesk SSO enables SSO for freshdesk from your django application.
Home-page: https://github.com/soundradix-website/django-freshdesk-sso
License: MIT
Keywords: django,freshdesk,sso
Author: Sound Radix
Author-email: soundradix@soundradix.com
Requires-Python: >=3.7,<4.0
Classifier: License :: OSI Approved :: MIT License
Classifier: Programming Language :: Python :: 3
Classifier: Programming Language :: Python :: 3.7
Classifier: Programming Language :: Python :: 3.8
Classifier: Programming Language :: Python :: 3.9
Requires-Dist: Django (>=2.2.17,<3.0.0)
Project-URL: Repository, https://github.com/soundradix-website/django-freshdesk-sso
